nx_hif/__init__.py
nx_hif/hif.py
nx_hif/readwrite.py
nx_hif/test_readwrite.py
nx_hif/test_standard_cases.py
nx_hif-0.0.11.dist-info/METADATA
nx_hif-0.0.11.dist-info/WHEEL
nx_hif-0.0.11.dist-info/licenses/LICENSE
nx_hif-0.0.11.dist-info/RECORD
