Metadata-Version: 2.4
Name: nx_hif
Version: 0.0.11
Summary: Higher-order networks for NetworkX using HIF
Project-URL: Source, https://github.com/colltoaction/nx_hif
License-File: LICENSE
Requires-Dist: networkx
